czh_bailian_mcp_server/__init__.py
czh_bailian_mcp_server/server.py
czh_bailian_mcp_server-0.1.0.dist-info/METADATA
czh_bailian_mcp_server-0.1.0.dist-info/WHEEL
czh_bailian_mcp_server-0.1.0.dist-info/entry_points.txt
czh_bailian_mcp_server-0.1.0.dist-info/RECORD
